oect_excel_processor/__init__.py
oect_excel_processor/batch_processor.py
oect_excel_processor/cli.py
oect_excel_processor/excel_processor.py
oect_excel_processor/examples/batch_processing_example.py
oect_excel_processor/examples/multiprocessing_comparison.py
oect_excel_processor/examples/single_file_example.py
oect_excel_processor-0.1.0.dist-info/LICENSE
oect_excel_processor-0.1.0.dist-info/METADATA
oect_excel_processor-0.1.0.dist-info/WHEEL
oect_excel_processor-0.1.0.dist-info/entry_points.txt
oect_excel_processor-0.1.0.dist-info/top_level.txt
oect_excel_processor-0.1.0.dist-info/RECORD
